deeppyer/__init__.py
deeppyer/cli.py
deeppyer/flare.png
deeppyer-1.0.1.dist-info/LICENSE
deeppyer-1.0.1.dist-info/METADATA
deeppyer-1.0.1.dist-info/WHEEL
deeppyer-1.0.1.dist-info/entry_points.txt
deeppyer-1.0.1.dist-info/top_level.txt
deeppyer-1.0.1.dist-info/RECORD
