Metadata-Version: 2.1
Name: deeppyer
Version: 1.0.1
Summary: Deepfry images in Python.
Home-page: https://github.com/Ovyerus/deeppyer
Author: Ovyerus
Author-email: iamovyerus@gmail.com
License: MIT
Keywords: image manipulation deepfry meme
Platform: UNKNOWN
Classifier: Intended Audience :: Developers
Classifier: Programming Language :: Python :: 3.6
Classifier: Programming Language :: Python :: 3.7
Classifier: License :: OSI Approved :: MIT License
Classifier: Operating System :: OS Independent
Classifier: Development Status :: 5 - Production/Stable
Classifier: Topic :: Multimedia :: Graphics
Classifier: Typing :: Typed
Requires-Python: >=3.6
